[
    {
        "availablecolors": "red,yellow,green,blue",
        "levelnum": 1,
        "fireflycolors": "red,red,green,green,yellow,yellow,blue",
        "slotcount": 7
    },
    {
        "slot": "1,0,blue,0,16,2"
    },
    {
        "slot": "2,0,blue,0,64,2"
    },
    {
        "slot": "3,0,green,0,40,44"
    },
    {
        "slot": "4,0,blue,0,40,93"
    },
    {
        "slot": "5,0,green,0,70,60"
    },
    {
        "slot": "6,0,blue,0,100,99"
    },
    {
        "slot": "7,0,yellow,0,15,90"
    },
    {
        "line": "16,2,28,14,1"
    },
    {
        "line": "16,2,17,17,1"
    },
    {
        "line": "33,34,26,32,1"
    },
    {
        "line": "64,2,52,14,2"
    },
    {
        "line": "64,2,63,17,2"
    },
    {
        "line": "47,34,54,32,2"
    },
    {
        "line": "40,44,24,38,3"
    },
    {
        "line": "40,44,28,14,3"
    },
    {
        "line": "40,44,52,14,3"
    },
    {
        "line": "40,44,56,38,3"
    },
    {
        "line": "40,10,17,17,3"
    },
    {
        "line": "40,10,63,17,3"
    },
    {
        "line": "17,29,17,17,3"
    },
    {
        "line": "17,29,24,38,3"
    },
    {
        "line": "63,29,63,17,3"
    },
    {
        "line": "63,29,56,38,3"
    },
    {
        "line": "31,60,24,38,4"
    },
    {
        "line": "31,60,40,44,4"
    },
    {
        "line": "31,60,40,93,4"
    },
    {
        "line": "31,60,30,99,4"
    },
    {
        "line": "49,60,40,44,4"
    },
    {
        "line": "49,60,40,93,4"
    },
    {
        "line": "49,60,56,38,4"
    },
    {
        "line": "49,60,50,99,4"
    },
    {
        "line": "40,93,40,44,4"
    },
    {
        "line": "40,93,30,99,4"
    },
    {
        "line": "40,93,50,99,4"
    },
    {
        "line": "30,99,50,99,4"
    },
    {
        "line": "70,60,56,38,5"
    },
    {
        "line": "70,60,50,99,5"
    },
    {
        "line": "70,60,70,88,5"
    },
    {
        "line": "24,38,30,99,5"
    },
    {
        "line": "56,38,50,99,5"
    },
    {
        "line": "63,99,100,99,6"
    },
    {
        "line": "70,88,50,99,6"
    },
    {
        "line": "70,88,63,99,6"
    },
    {
        "line": "70,88,88,99,6"
    },
    {
        "line": "70,88,100,99,6"
    },
    {
        "line": "89,91,100,99,6"
    },
    {
        "line": "89,91,89,95,6"
    },
    {
        "line": "27,90,3,90,7"
    },
    {
        "line": "22,99,8,81,7"
    },
    {
        "line": "22,81,8,99,7"
    },
    {
        "line": "22,81,27,90,7"
    },
    {
        "line": "27,90,22,99,7"
    },
    {
        "line": "22,99,8,99,7"
    },
    {
        "line": "8,99,3,90,7"
    },
    {
        "line": "3,90,8,81,7"
    },
    {
        "line": "8,81,22,81,7"
    }
]